[{"Well Name": "BEAL #1", "Recent Month P&L": 26985.048125, "YTD Gain/Loss": 225610.8775000001, "Date": "Dec 2024", "YTD P&L": 225610.8775000001}, {"Well Name": "Benge Unit #1H", "Recent Month P&L": 16004.75391875, "YTD Gain/Loss": 166794.1604687501, "Date": "Dec 2024", "YTD P&L": 166794.1604687501}, {"Well Name": "BRADSHAW #1", "Recent Month P&L": 173.683977204, "YTD Gain/Loss": 29093.2212062445, "Date": "Dec 2024", "YTD P&L": 29093.2212062445}, {"Well Name": "CK #1", "Recent Month P&L": 11493.0259032, "YTD Gain/Loss": 41348.7630078, "Date": "Dec 2024", "YTD P&L": 41348.7630078}, {"Well Name": "Coffman #1H", "Recent Month P&L": 30231.9945, "YTD Gain/Loss": 214420.0009, "Date": "Dec 2024", "YTD P&L": 214420.0009}, {"Well Name": "DELLA #1", "Recent Month P&L": 24793.5673971768, "YTD Gain/Loss": 229874.4639039576, "Date": "Dec 2024", "YTD P&L": 229874.4639039576}, {"Well Name": "DRAKE #1", "Recent Month P&L": 1855.4633706384, "YTD Gain/Loss": 103215.3232160802, "Date": "Dec 2024", "YTD P&L": 103215.3232160802}, {"Well Name": "DRAKE #2", "Recent Month P&L": 32762.867449161, "YTD Gain/Loss": 248902.501452759, "Date": "Dec 2024", "YTD P&L": 248902.501452759}, {"Well Name": "FLORA #1", "Recent Month P&L": 35028.20625, "YTD Gain/Loss": 362224.15, "Date": "Dec 2024", "YTD P&L": 362224.15}, {"Well Name": "FLOYD #1", "Recent Month P&L": 1206.84322412, "YTD Gain/Loss": -4961.12422824, "Date": "Dec 2024", "YTD P&L": -4961.12422824}, {"Well Name": "Harrison #1H", "Recent Month P&L": -5402.1149967, "YTD Gain/Loss": 1952.316847175, "Date": "Dec 2024", "YTD P&L": 1952.316847175}, {"Well Name": "Harrison #2H", "Recent Month P&L": 27132.61218325, "YTD Gain/Loss": 143470.7685216, "Date": "Dec 2024", "YTD P&L": 143470.7685216}, {"Well Name": "HAYES #1", "Recent Month P&L": 25091.57150742, "YTD Gain/Loss": 253999.1955070896, "Date": "Dec 2024", "YTD P&L": 253999.1955070896}, {"Well Name": "HAYES #2", "Recent Month P&L": 17684.5366823184, "YTD Gain/Loss": 258342.4830827768, "Date": "Dec 2024", "YTD P&L": 258342.4830827768}, {"Well Name": "Herbich #2H", "Recent Month P&L": 17673.66778874, "YTD Gain/Loss": 140494.630615486, "Date": "Dec 2024", "YTD P&L": 140494.630615486}, {"Well Name": "ISBELL #1", "Recent Month P&L": 6429.04625, "YTD Gain/Loss": 139072.498125, "Date": "Dec 2024", "YTD P&L": 139072.498125}, {"Well Name": "JAM #1", "Recent Month P&L": 12953.010768609, "YTD Gain/Loss": 193389.4941159256, "Date": "Dec 2024", "YTD P&L": 193389.4941159256}, {"Well Name": "JOYCE #1", "Recent Month P&L": 3827.1618347525, "YTD Gain/Loss": -18790.5465375125, "Date": "Dec 2024", "YTD P&L": -18790.5465375125}, {"Well Name": "KAGG #1", "Recent Month P&L": 8279.7638009714, "YTD Gain/Loss": 40537.959417504, "Date": "Dec 2024", "YTD P&L": 40537.959417504}, {"Well Name": "KAGG #2", "Recent Month P&L": 7728.758096064, "YTD Gain/Loss": 48729.2460920307, "Date": "Dec 2024", "YTD P&L": 48729.2460920307}, {"Well Name": "KENNEDY #1", "Recent Month P&L": 13976.3897499052, "YTD Gain/Loss": 173372.5132100463, "Date": "Dec 2024", "YTD P&L": 173372.5132100463}, {"Well Name": "MT Unit #1H", "Recent Month P&L": 21589.091595359, "YTD Gain/Loss": 216607.475061321, "Date": "Dec 2024", "YTD P&L": 216607.475061321}, {"Well Name": "Myrtle #1", "Recent Month P&L": -5770.2667061828, "YTD Gain/Loss": -44655.2075449748, "Date": "Dec 2024", "YTD P&L": -44655.2075449748}, {"Well Name": "NEVILL #1", "Recent Month P&L": 4512.096566978, "YTD Gain/Loss": 156820.770902819, "Date": "Dec 2024", "YTD P&L": 156820.770902819}, {"Well Name": "NEVILLE-BEAL #1", "Recent Month P&L": 0, "YTD Gain/Loss": -2588.98, "Date": "Dec 2024", "YTD P&L": -2588.98}, {"Well Name": "PETERS #6", "Recent Month P&L": 11786.434, "YTD Gain/Loss": 108978.016, "Date": "Dec 2024", "YTD P&L": 108978.016}, {"Well Name": "PETERS #7", "Recent Month P&L": 13895.626, "YTD Gain/Loss": 137027.37, "Date": "Dec 2024", "YTD P&L": 137027.37}, {"Well Name": "POST OAK #1", "Recent Month P&L": 20357.9893899725, "YTD Gain/Loss": 68499.068784646, "Date": "Dec 2024", "YTD P&L": 68499.068784646}, {"Well Name": "POST OAK #2", "Recent Month P&L": 33164.2251318225, "YTD Gain/Loss": 371595.922301315, "Date": "Dec 2024", "YTD P&L": 371595.922301315}, {"Well Name": "RA #1", "Recent Month P&L": -6071.188229688, "YTD Gain/Loss": -30199.2982618114, "Date": "Dec 2024", "YTD P&L": -30199.2982618114}, {"Well Name": "Clary RB #1", "Recent Month P&L": 49241.679279859, "YTD Gain/Loss": 319642.6200538371, "Date": "Dec 2024", "YTD P&L": 319642.6200538371}, {"Well Name": "RUEN #1", "Recent Month P&L": 26921.5825149674, "YTD Gain/Loss": 207599.7230124103, "Date": "Dec 2024", "YTD P&L": 207599.7230124103}, {"Well Name": "RUEN #2", "Recent Month P&L": 7263.936019321, "YTD Gain/Loss": 166485.5000091134, "Date": "Dec 2024", "YTD P&L": 166485.5000091134}, {"Well Name": "RUEN #3X", "Recent Month P&L": 6973.6482101007, "YTD Gain/Loss": 39819.5007235755, "Date": "Dec 2024", "YTD P&L": 39819.5007235755}, {"Well Name": "SUMMIT DRAKE FARMOUT", "Recent Month P&L": 0, "YTD Gain/Loss": 0, "Date": "Dec 2024", "YTD P&L": 0}, {"Well Name": "SUTTON #1", "Recent Month P&L": 50866.2, "YTD Gain/Loss": 112921.6, "Date": "Dec 2024", "YTD P&L": 112921.6}, {"Well Name": "SUTTON #2", "Recent Month P&L": 10527.505, "YTD Gain/Loss": 138571.2775, "Date": "Dec 2024", "YTD P&L": 138571.2775}, {"Well Name": "SUTTON #3", "Recent Month P&L": -4907.8025, "YTD Gain/Loss": -44309.035, "Date": "Dec 2024", "YTD P&L": -44309.035}, {"Well Name": "Total", "Recent Month P&L": 641852.1203307922, "YTD Gain/Loss": 5746091.741526921, "Date": "Dec 2024", "YTD P&L": 5746091.741526921}, {"Well Name": "Watson-Buck #1H", "Recent Month P&L": 5873.185, "YTD Gain/Loss": -23171.435, "Date": "Dec 2024", "YTD P&L": -23171.435}, {"Well Name": "WEBB #1", "Recent Month P&L": -964.2247133424, "YTD Gain/Loss": 27746.6144410504, "Date": "Dec 2024", "YTD P&L": 27746.6144410504}, {"Well Name": "WHITE-SPRINGER #1", "Recent Month P&L": 17998.7834512284, "YTD Gain/Loss": 174823.8630687234, "Date": "Dec 2024", "YTD P&L": 174823.8630687234}, {"Well Name": "Wiese #1H", "Recent Month P&L": 13755.392687585, "YTD Gain/Loss": 106887.83202149, "Date": "Dec 2024", "YTD P&L": 106887.83202149}, {"Well Name": "WILLIAM #1", "Recent Month P&L": 18728.339038848, "YTD Gain/Loss": 210737.029487584, "Date": "Dec 2024", "YTD P&L": 210737.029487584}, {"Well Name": "WILLIE #1", "Recent Month P&L": 12984.9383426331, "YTD Gain/Loss": 168173.4381962491, "Date": "Dec 2024", "YTD P&L": 168173.4381962491}, {"Well Name": "WS #1", "Recent Month P&L": 17215.09247075, "YTD Gain/Loss": 166985.1793451, "Date": "Dec 2024", "YTD P&L": 166985.1793451}, {"Well Name": "Aaron #1", "Recent Month P&L": -26311.1025, "YTD Gain/Loss": 270171.4450000001, "Date": "Dec 2024", "YTD P&L": 270171.4450000001}, {"Well Name": "Allen #1", "Recent Month P&L": 0, "YTD Gain/Loss": -717.07, "Date": "Dec 2024", "YTD P&L": -717.07}, {"Well Name": "Aniken #1", "Recent Month P&L": 5766.45925, "YTD Gain/Loss": 35318.889, "Date": "Dec 2024", "YTD P&L": 35318.889}, {"Well Name": "Anna Louisa #1", "Recent Month P&L": 0, "YTD Gain/Loss": 0, "Date": "Dec 2024", "YTD P&L": 0}, {"Well Name": "Annpick #1", "Recent Month P&L": -9667.5461569084, "YTD Gain/Loss": 7217.5854973456, "Date": "Dec 2024", "YTD P&L": 7217.5854973456}, {"Well Name": "Beeler #16 RE", "Recent Month P&L": 99428.263724625, "YTD Gain/Loss": 1361869.79158144, "Date": "Dec 2024", "YTD P&L": 1361869.79158144}, {"Well Name": "BMMP #1", "Recent Month P&L": -1471, "YTD Gain/Loss": -12874.06, "Date": "Dec 2024", "YTD P&L": -12874.06}, {"Well Name": "BMMP #3", "Recent Month P&L": 0, "YTD Gain/Loss": 10150, "Date": "Dec 2024", "YTD P&L": 10150}, {"Well Name": "BRUCE WEAVER #1", "Recent Month P&L": 20127.427151168, "YTD Gain/Loss": 40071.4893555839, "Date": "Dec 2024", "YTD P&L": 40071.4893555839}, {"Well Name": "BRUCE WEAVER #2 RE", "Recent Month P&L": 51634.366987648, "YTD Gain/Loss": 1529891.3967267198, "Date": "Dec 2024", "YTD P&L": 1529891.3967267198}, {"Well Name": "Balfour #1", "Recent Month P&L": 24495.3031393459, "YTD Gain/Loss": 361988.9487637805, "Date": "Dec 2024", "YTD P&L": 361988.9487637805}, {"Well Name": "Barrier #1", "Recent Month P&L": 7464.020358788, "YTD Gain/Loss": 70204.8310061768, "Date": "Dec 2024", "YTD P&L": 70204.8310061768}, {"Well Name": "Beeler Ranch #1", "Recent Month P&L": 3540.1100921354, "YTD Gain/Loss": 18886.4485149442, "Date": "Dec 2024", "YTD P&L": 18886.4485149442}, {"Well Name": "Bermuda #1", "Recent Month P&L": 4171.1731065536, "YTD Gain/Loss": -4207.2778540502, "Date": "Dec 2024", "YTD P&L": -4207.2778540502}, {"Well Name": "Betty #1", "Recent Month P&L": 0, "YTD Gain/Loss": 3918.85, "Date": "Dec 2024", "YTD P&L": 3918.85}, {"Well Name": "Big Sonny #1", "Recent Month P&L": 4096.9575, "YTD Gain/Loss": 50977.145, "Date": "Dec 2024", "YTD P&L": 50977.145}, {"Well Name": "Blackmon #1", "Recent Month P&L": 25142.66494115, "YTD Gain/Loss": 307049.39886325, "Date": "Dec 2024", "YTD P&L": 307049.39886325}, {"Well Name": "Blas Reyes #1", "Recent Month P&L": -2430.91, "YTD Gain/Loss": -56410.005, "Date": "Dec 2024", "YTD P&L": -56410.005}, {"Well Name": "Bond #1", "Recent Month P&L": -2639.76, "YTD Gain/Loss": 35215.1732289181, "Date": "Dec 2024", "YTD P&L": 35215.1732289181}, {"Well Name": "Box #1", "Recent Month P&L": 0, "YTD Gain/Loss": -2137.27, "Date": "Dec 2024", "YTD P&L": -2137.27}, {"Well Name": "Branton #1", "Recent Month P&L": -266, "YTD Gain/Loss": -1923.5402865289, "Date": "Dec 2024", "YTD P&L": -1923.5402865289}, {"Well Name": "Buck #1", "Recent Month P&L": 0, "YTD Gain/Loss": 0, "Date": "Dec 2024", "YTD P&L": 0}, {"Well Name": "Burns Ranch #2", "Recent Month P&L": 97728.6344567841, "YTD Gain/Loss": 780986.4293880292, "Date": "Dec 2024", "YTD P&L": 780986.4293880292}, {"Well Name": "Burns Ranch GT #1", "Recent Month P&L": -266, "YTD Gain/Loss": -9733.49, "Date": "Dec 2024", "YTD P&L": -9733.49}, {"Well Name": "CMWW #1", "Recent Month P&L": 36466.40308796, "YTD Gain/Loss": 681586.66345424, "Date": "Dec 2024", "YTD P&L": 681586.66345424}, {"Well Name": "CMWW #2", "Recent Month P&L": 190711.26827776, "YTD Gain/Loss": 5569626.018885121, "Date": "Dec 2024", "YTD P&L": 5569626.018885121}, {"Well Name": "CR #101", "Recent Month P&L": 15699.161963733, "YTD Gain/Loss": 208257.3495885248, "Date": "Dec 2024", "YTD P&L": 208257.3495885248}, {"Well Name": "CR #201", "Recent Month P&L": 12196.6793856593, "YTD Gain/Loss": 175086.6519862308, "Date": "Dec 2024", "YTD P&L": 175086.6519862308}, {"Well Name": "CR #301", "Recent Month P&L": 26833.0385469227, "YTD Gain/Loss": 384989.2496759256, "Date": "Dec 2024", "YTD P&L": 384989.2496759256}, {"Well Name": "CR #302", "Recent Month P&L": 23340.7916610849, "YTD Gain/Loss": 257705.1934048649, "Date": "Dec 2024", "YTD P&L": 257705.1934048649}, {"Well Name": "CR #401", "Recent Month P&L": -2553.08, "YTD Gain/Loss": 4879.7956884374, "Date": "Dec 2024", "YTD P&L": 4879.7956884374}, {"Well Name": "CR #501", "Recent Month P&L": 5033.6339057974, "YTD Gain/Loss": 7649.7940971787, "Date": "Dec 2024", "YTD P&L": 7649.7940971787}, {"Well Name": "CR #939", "Recent Month P&L": 22295.0167067619, "YTD Gain/Loss": 495028.3133646579, "Date": "Dec 2024", "YTD P&L": 495028.3133646579}, {"Well Name": "CR 1148H", "Recent Month P&L": 0, "YTD Gain/Loss": -308.13, "Date": "Dec 2024", "YTD P&L": -308.13}, {"Well Name": "CR 447H", "Recent Month P&L": 0, "YTD Gain/Loss": 0, "Date": "Dec 2024", "YTD P&L": 0}, {"Well Name": "CT #1", "Recent Month P&L": 35074.175240278, "YTD Gain/Loss": 696823.1257281105, "Date": "Dec 2024", "YTD P&L": 696823.1257281105}, {"Well Name": "Cannan #1", "Recent Month P&L": -8995.29, "YTD Gain/Loss": 73531.3238833722, "Date": "Dec 2024", "YTD P&L": 73531.3238833722}, {"Well Name": "Carolpick #1", "Recent Month P&L": 27206.405, "YTD Gain/Loss": 209767.795, "Date": "Dec 2024", "YTD P&L": 209767.795}, {"Well Name": "Carolyn #1", "Recent Month P&L": 16519.22, "YTD Gain/Loss": 336359.5275, "Date": "Dec 2024", "YTD P&L": 336359.5275}, {"Well Name": "Cenizo #1", "Recent Month P&L": 4257.3075, "YTD Gain/Loss": 19406.8575, "Date": "Dec 2024", "YTD P&L": 19406.8575}, {"Well Name": "Chad #1", "Recent Month P&L": -3810.4125, "YTD Gain/Loss": 2109.855, "Date": "Dec 2024", "YTD P&L": 2109.855}, {"Well Name": "Charles B #1", "Recent Month P&L": 17557.084487994, "YTD Gain/Loss": 174645.224965002, "Date": "Dec 2024", "YTD P&L": 174645.224965002}, {"Well Name": "Circle T #1", "Recent Month P&L": -12988.4339111, "YTD Gain/Loss": 273945.82417715, "Date": "Dec 2024", "YTD P&L": 273945.82417715}, {"Well Name": "Clayton #1", "Recent Month P&L": 0, "YTD Gain/Loss": 0, "Date": "Dec 2024", "YTD P&L": 0}, {"Well Name": "Cornett #1", "Recent Month P&L": -4678.49, "YTD Gain/Loss": -220128.8102002648, "Date": "Dec 2024", "YTD P&L": -220128.8102002648}, {"Well Name": "Cross S #1", "Recent Month P&L": 6195.3459662007, "YTD Gain/Loss": 24920.7348741678, "Date": "Dec 2024", "YTD P&L": 24920.7348741678}, {"Well Name": "DIXONDALE #1", "Recent Month P&L": 81751.5160619851, "YTD Gain/Loss": 1784868.3767354898, "Date": "Dec 2024", "YTD P&L": 1784868.3767354898}, {"Well Name": "Dale #1", "Recent Month P&L": -4308.609217603, "YTD Gain/Loss": -13255.720325517, "Date": "Dec 2024", "YTD P&L": -13255.720325517}, {"Well Name": "Dial #1", "Recent Month P&L": 0, "YTD Gain/Loss": 0, "Date": "Dec 2024", "YTD P&L": 0}, {"Well Name": "Dial #1 ST", "Recent Month P&L": 4797.2828376058, "YTD Gain/Loss": -4082.7568516452, "Date": "Dec 2024", "YTD P&L": -4082.7568516452}, {"Well Name": "Dillard #1", "Recent Month P&L": 11579.0170746431, "YTD Gain/Loss": 54093.1349707436, "Date": "Dec 2024", "YTD P&L": 54093.1349707436}, {"Well Name": "Drinkard #1", "Recent Month P&L": 74413.0259143189, "YTD Gain/Loss": 969309.6950716742, "Date": "Dec 2024", "YTD P&L": 969309.6950716742}, {"Well Name": "Dunkle #2", "Recent Month P&L": -3143.86, "YTD Gain/Loss": 55992.3528828388, "Date": "Dec 2024", "YTD P&L": 55992.3528828388}, {"Well Name": "Dunlap #1", "Recent Month P&L": -2949.7425, "YTD Gain/Loss": 24074.795, "Date": "Dec 2024", "YTD P&L": 24074.795}, {"Well Name": "Dyess #1", "Recent Month P&L": -2850.68, "YTD Gain/Loss": 9469.6938284065, "Date": "Dec 2024", "YTD P&L": 9469.6938284065}, {"Well Name": "Eileen #1", "Recent Month P&L": 12068.1528031996, "YTD Gain/Loss": 64925.083899451, "Date": "Dec 2024", "YTD P&L": 64925.083899451}, {"Well Name": "Evergreen #1", "Recent Month P&L": 5928.0325, "YTD Gain/Loss": 65352.795, "Date": "Dec 2024", "YTD P&L": 65352.795}, {"Well Name": "FMMP #1", "Recent Month P&L": 0, "YTD Gain/Loss": 0, "Date": "Dec 2024", "YTD P&L": 0}, {"Well Name": "Fatheree #1", "Recent Month P&L": 64920.9806063187, "YTD Gain/Loss": 1140985.514216071, "Date": "Dec 2024", "YTD P&L": 1140985.514216071}, {"Well Name": "Flower #1", "Recent Month P&L": 5538.14, "YTD Gain/Loss": 117403.7875, "Date": "Dec 2024", "YTD P&L": 117403.7875}, {"Well Name": "Flying G #1", "Recent Month P&L": -786.09, "YTD Gain/Loss": -2854.12, "Date": "Dec 2024", "YTD P&L": -2854.12}, {"Well Name": "Gail #1", "Recent Month P&L": 12621.6375, "YTD Gain/Loss": 178654.5049999999, "Date": "Dec 2024", "YTD P&L": 178654.5049999999}, {"Well Name": "Gil #1", "Recent Month P&L": 4232.41844, "YTD Gain/Loss": -52521.258911, "Date": "Dec 2024", "YTD P&L": -52521.258911}, {"Well Name": "Grissom #1", "Recent Month P&L": -36769.98, "YTD Gain/Loss": 21285.2775008855, "Date": "Dec 2024", "YTD P&L": 21285.2775008855}, {"Well Name": "Haby #1", "Recent Month P&L": 0, "YTD Gain/Loss": -1155.66, "Date": "Dec 2024", "YTD P&L": -1155.66}, {"Well Name": "Heitz #1", "Recent Month P&L": 0, "YTD Gain/Loss": 0, "Date": "Dec 2024", "YTD P&L": 0}, {"Well Name": "Huber #1", "Recent Month P&L": 0, "YTD Gain/Loss": -1111.22, "Date": "Dec 2024", "YTD P&L": -1111.22}, {"Well Name": "J Beeler #1", "Recent Month P&L": 54408.1970266505, "YTD Gain/Loss": 353673.0015559596, "Date": "Dec 2024", "YTD P&L": 353673.0015559596}, {"Well Name": "JIC #1", "Recent Month P&L": 8525.8121442221, "YTD Gain/Loss": 790988.5536639767, "Date": "Dec 2024", "YTD P&L": 790988.5536639767}, {"Well Name": "JIC Buda #1", "Recent Month P&L": 7577.6388488744, "YTD Gain/Loss": 90428.4854146384, "Date": "Dec 2024", "YTD P&L": 90428.4854146384}, {"Well Name": "JJ #1", "Recent Month P&L": -15948.7570532285, "YTD Gain/Loss": -51212.3489819015, "Date": "Dec 2024", "YTD P&L": -51212.3489819015}, {"Well Name": "Jessica #1", "Recent Month P&L": 24207.8875, "YTD Gain/Loss": 208492.645, "Date": "Dec 2024", "YTD P&L": 208492.645}, {"Well Name": "Joe #1", "Recent Month P&L": -266, "YTD Gain/Loss": -3301.80848282, "Date": "Dec 2024", "YTD P&L": -3301.80848282}, {"Well Name": "Joseph #1", "Recent Month P&L": -3182.4, "YTD Gain/Loss": -21030.83121182, "Date": "Dec 2024", "YTD P&L": -21030.83121182}, {"Well Name": "Jred #1", "Recent Month P&L": 5683.36, "YTD Gain/Loss": 76319.155, "Date": "Dec 2024", "YTD P&L": 76319.155}, {"Well Name": "KLEIMANN #3RE", "Recent Month P&L": 1167870.3283102678, "YTD Gain/Loss": 4765943.377351949, "Date": "Dec 2024", "YTD P&L": 4765943.377351949}, {"Well Name": "Kay #1", "Recent Month P&L": -415.7219587972, "YTD Gain/Loss": -84289.9118908021, "Date": "Dec 2024", "YTD P&L": -84289.9118908021}, {"Well Name": "Kiley #1", "Recent Month P&L": 26490.6575, "YTD Gain/Loss": 301982.36, "Date": "Dec 2024", "YTD P&L": 301982.36}, {"Well Name": "Kincaid #1", "Recent Month P&L": 0, "YTD Gain/Loss": 0, "Date": "Dec 2024", "YTD P&L": 0}, {"Well Name": "Kirby #1", "Recent Month P&L": 0, "YTD Gain/Loss": -1088.05, "Date": "Dec 2024", "YTD P&L": -1088.05}, {"Well Name": "Kleimann #1", "Recent Month P&L": 60712.4210636538, "YTD Gain/Loss": 730826.3998159025, "Date": "Dec 2024", "YTD P&L": 730826.3998159025}, {"Well Name": "Kleimann #3", "Recent Month P&L": 0, "YTD Gain/Loss": -3955.58, "Date": "Dec 2024", "YTD P&L": -3955.58}, {"Well Name": "LAMB #1", "Recent Month P&L": -11918.12, "YTD Gain/Loss": -81756.00162732, "Date": "Dec 2024", "YTD P&L": -81756.00162732}, {"Well Name": "LT #1", "Recent Month P&L": 5757.3482553436, "YTD Gain/Loss": 59587.7085648539, "Date": "Dec 2024", "YTD P&L": 59587.7085648539}, {"Well Name": "La Rosita #1 RE", "Recent Month P&L": 26115.841971834, "YTD Gain/Loss": 718270.841148242, "Date": "Dec 2024", "YTD P&L": 718270.841148242}, {"Well Name": "Lackey Five #1", "Recent Month P&L": 13798.2465834624, "YTD Gain/Loss": 175827.0540777654, "Date": "Dec 2024", "YTD P&L": 175827.0540777654}, {"Well Name": "Lander #1", "Recent Month P&L": 17435.2375, "YTD Gain/Loss": -44161.09, "Date": "Dec 2024", "YTD P&L": -44161.09}, {"Well Name": "Lansford #1", "Recent Month P&L": 0, "YTD Gain/Loss": 0, "Date": "Dec 2024", "YTD P&L": 0}, {"Well Name": "Leary Trust #1", "Recent Month P&L": 5810.137803926, "YTD Gain/Loss": 71412.306139562, "Date": "Dec 2024", "YTD P&L": 71412.306139562}, {"Well Name": "Lisa #1", "Recent Month P&L": 0, "YTD Gain/Loss": 0, "Date": "Dec 2024", "YTD P&L": 0}, {"Well Name": "Little 179 #1", "Recent Month P&L": 92440.8375, "YTD Gain/Loss": 735659.6874999998, "Date": "Dec 2024", "YTD P&L": 735659.6874999998}, {"Well Name": "Lochte #1", "Recent Month P&L": 13962.938066, "YTD Gain/Loss": 202290.382227, "Date": "Dec 2024", "YTD P&L": 202290.382227}, {"Well Name": "MDB #1", "Recent Month P&L": 21319.6262255735, "YTD Gain/Loss": 268298.5020837337, "Date": "Dec 2024", "YTD P&L": 268298.5020837337}, {"Well Name": "Marguerite #1", "Recent Month P&L": 5334.2325, "YTD Gain/Loss": 14914.1075, "Date": "Dec 2024", "YTD P&L": 14914.1075}, {"Well Name": "Marpick #1", "Recent Month P&L": 2520.6775, "YTD Gain/Loss": -25319.18, "Date": "Dec 2024", "YTD P&L": -25319.18}, {"Well Name": "Marrs #1", "Recent Month P&L": 48144.4352061092, "YTD Gain/Loss": 613962.1316488734, "Date": "Dec 2024", "YTD P&L": 613962.1316488734}, {"Well Name": "McLean #1", "Recent Month P&L": 0, "YTD Gain/Loss": -995.89, "Date": "Dec 2024", "YTD P&L": -995.89}, {"Well Name": "Molak #1", "Recent Month P&L": -15463.98, "YTD Gain/Loss": -9065.04, "Date": "Dec 2024", "YTD P&L": -9065.04}, {"Well Name": "Montemayor #1", "Recent Month P&L": -266, "YTD Gain/Loss": -4522.58, "Date": "Dec 2024", "YTD P&L": -4522.58}, {"Well Name": "Moreland #1", "Recent Month P&L": -4472.99, "YTD Gain/Loss": 54019.0596, "Date": "Dec 2024", "YTD P&L": 54019.0596}, {"Well Name": "PC #1", "Recent Month P&L": -3770.465, "YTD Gain/Loss": 86756.5025, "Date": "Dec 2024", "YTD P&L": 86756.5025}, {"Well Name": "PFEIFFER-BYRD #1", "Recent Month P&L": 136632.4435080375, "YTD Gain/Loss": 2212428.6548714843, "Date": "Dec 2024", "YTD P&L": 2212428.6548714843}, {"Well Name": "Palm #1", "Recent Month P&L": -1044.3, "YTD Gain/Loss": -18783.3357017718, "Date": "Dec 2024", "YTD P&L": -18783.3357017718}, {"Well Name": "Parkway #1 RE", "Recent Month P&L": 42620.199749715, "YTD Gain/Loss": 859209.2769175922, "Date": "Dec 2024", "YTD P&L": 859209.2769175922}, {"Well Name": "Pecan Grove #1", "Recent Month P&L": -2156.87, "YTD Gain/Loss": -5417.99, "Date": "Dec 2024", "YTD P&L": -5417.99}, {"Well Name": "Pfeiffer #1", "Recent Month P&L": 5695.97, "YTD Gain/Loss": 74368.18, "Date": "Dec 2024", "YTD P&L": 74368.18}, {"Well Name": "Pickens #1", "Recent Month P&L": -3215.74, "YTD Gain/Loss": -22051.26858, "Date": "Dec 2024", "YTD P&L": -22051.26858}, {"Well Name": "Pickens Ranch #2H", "Recent Month P&L": 0, "YTD Gain/Loss": 0, "Date": "Dec 2024", "YTD P&L": 0}, {"Well Name": "Pickens Weaver #1", "Recent Month P&L": 1756.02, "YTD Gain/Loss": 84387.24, "Date": "Dec 2024", "YTD P&L": 84387.24}, {"Well Name": "Pickwill #1", "Recent Month P&L": 14437.53, "YTD Gain/Loss": 148122.2575, "Date": "Dec 2024", "YTD P&L": 148122.2575}, {"Well Name": "Preston #1", "Recent Month P&L": -266, "YTD Gain/Loss": 11485.591235866, "Date": "Dec 2024", "YTD P&L": 11485.591235866}, {"Well Name": "Pritchett #1", "Recent Month P&L": 0, "YTD Gain/Loss": 0, "Date": "Dec 2024", "YTD P&L": 0}, {"Well Name": "RAB #1", "Recent Month P&L": 63112.041984, "YTD Gain/Loss": 553466.2209103998, "Date": "Dec 2024", "YTD P&L": 553466.2209103998}, {"Well Name": "RAB #2", "Recent Month P&L": 60875.5592991428, "YTD Gain/Loss": 1049419.4888161144, "Date": "Dec 2024", "YTD P&L": 1049419.4888161144}, {"Well Name": "RAB #3", "Recent Month P&L": 57226.4289383774, "YTD Gain/Loss": 416467.723530473, "Date": "Dec 2024", "YTD P&L": 416467.723530473}, {"Well Name": "RAB #4", "Recent Month P&L": 0, "YTD Gain/Loss": 0, "Date": "Dec 2024", "YTD P&L": 0}, {"Well Name": "Rhodes #1", "Recent Month P&L": -1120.68, "YTD Gain/Loss": -3877.6411941061, "Date": "Dec 2024", "YTD P&L": -3877.6411941061}, {"Well Name": "Richard #1", "Recent Month P&L": 28334.8111185851, "YTD Gain/Loss": 436428.3644175827, "Date": "Dec 2024", "YTD P&L": 436428.3644175827}, {"Well Name": "Richardson #1", "Recent Month P&L": 41511.86, "YTD Gain/Loss": 491112.1075, "Date": "Dec 2024", "YTD P&L": 491112.1075}, {"Well Name": "Rio Nueces #1", "Recent Month P&L": 0, "YTD Gain/Loss": 0, "Date": "Dec 2024", "YTD P&L": 0}, {"Well Name": "Ronald #1", "Recent Month P&L": 4414.4029747424, "YTD Gain/Loss": 89379.6405566576, "Date": "Dec 2024", "YTD P&L": 89379.6405566576}, {"Well Name": "Russell #1", "Recent Month P&L": -2027.1, "YTD Gain/Loss": -106530.9, "Date": "Dec 2024", "YTD P&L": -106530.9}, {"Well Name": "Ruth #1", "Recent Month P&L": 14990.3225, "YTD Gain/Loss": 141402.3275, "Date": "Dec 2024", "YTD P&L": 141402.3275}, {"Well Name": "Ruthpick #1", "Recent Month P&L": 8384.9875, "YTD Gain/Loss": 85391.495, "Date": "Dec 2024", "YTD P&L": 85391.495}, {"Well Name": "SUGAR RANCH #1", "Recent Month P&L": -18517.15417936, "YTD Gain/Loss": -717590.33780512, "Date": "Dec 2024", "YTD P&L": -717590.33780512}, {"Well Name": "Sansom #1", "Recent Month P&L": 21085.1091683608, "YTD Gain/Loss": 246319.8558486074, "Date": "Dec 2024", "YTD P&L": 246319.8558486074}, {"Well Name": "Solansky #1", "Recent Month P&L": 5743.1783119071, "YTD Gain/Loss": 90691.194079775, "Date": "Dec 2024", "YTD P&L": 90691.194079775}, {"Well Name": "Sugarland #1", "Recent Month P&L": -3508.32, "YTD Gain/Loss": 2707.365, "Date": "Dec 2024", "YTD P&L": 2707.365}, {"Well Name": "TJN UNIT #1", "Recent Month P&L": -162523.8075, "YTD Gain/Loss": -503448.245, "Date": "Dec 2024", "YTD P&L": -503448.245}, {"Well Name": "Thalmann #1 RE", "Recent Month P&L": 127302.9650578616, "YTD Gain/Loss": 521147.6051167886, "Date": "Dec 2024", "YTD P&L": 521147.6051167886}, {"Well Name": "Thompson #1", "Recent Month P&L": 0, "YTD Gain/Loss": -1336.79, "Date": "Dec 2024", "YTD P&L": -1336.79}, {"Well Name": "Thompson #2", "Recent Month P&L": -4832.25, "YTD Gain/Loss": -47946.0043732341, "Date": "Dec 2024", "YTD P&L": -47946.0043732341}, {"Well Name": "Thuss #1", "Recent Month P&L": -16195.72, "YTD Gain/Loss": -32287.0775, "Date": "Dec 2024", "YTD P&L": -32287.0775}, {"Well Name": "Tlapek #1", "Recent Month P&L": -8973.44, "YTD Gain/Loss": -41465.302453684, "Date": "Dec 2024", "YTD P&L": -41465.302453684}, {"Well Name": "Total", "Recent Month P&L": 2907248.739852386, "YTD Gain/Loss": 34554731.88328513, "Date": "Dec 2024", "YTD P&L": 34554731.88328513}, {"Well Name": "Triple J #2", "Recent Month P&L": -266, "YTD Gain/Loss": -8071.53, "Date": "Dec 2024", "YTD P&L": -8071.53}, {"Well Name": "Trotter #1", "Recent Month P&L": 5739.6275, "YTD Gain/Loss": 60849, "Date": "Dec 2024", "YTD P&L": 60849}, {"Well Name": "VRE Minerals #1", "Recent Month P&L": -810, "YTD Gain/Loss": -34473.6825, "Date": "Dec 2024", "YTD P&L": -34473.6825}, {"Well Name": "Vermillion #1", "Recent Month P&L": -1882.85, "YTD Gain/Loss": -19901.7375, "Date": "Dec 2024", "YTD P&L": -19901.7375}, {"Well Name": "Verna #1", "Recent Month P&L": 5034.2325, "YTD Gain/Loss": 5301.405, "Date": "Dec 2024", "YTD P&L": 5301.405}, {"Well Name": "White Marlin #1", "Recent Month P&L": -918, "YTD Gain/Loss": 600.7152175587, "Date": "Dec 2024", "YTD P&L": 600.7152175587}, {"Well Name": "Whittington #1", "Recent Month P&L": 4253.7245363144, "YTD Gain/Loss": -42018.074599384, "Date": "Dec 2024", "YTD P&L": -42018.074599384}, {"Well Name": "Woodward #1", "Recent Month P&L": 0, "YTD Gain/Loss": 7060.4, "Date": "Dec 2024", "YTD P&L": 7060.4}, {"Well Name": "Buchanan Unit #1", "Recent Month P&L": -2525.06, "YTD Gain/Loss": -23030.561726341, "Date": "Dec 2024", "YTD P&L": -23030.561726341}, {"Well Name": "Caldwell #1", "Recent Month P&L": 1263.7926787936, "YTD Gain/Loss": -33627.0699216768, "Date": "Dec 2024", "YTD P&L": -33627.0699216768}, {"Well Name": "Carroll Unit #1", "Recent Month P&L": -138.0003861582, "YTD Gain/Loss": 67009.2476896735, "Date": "Dec 2024", "YTD P&L": 67009.2476896735}, {"Well Name": "CHRISTOPHER #1", "Recent Month P&L": 0, "YTD Gain/Loss": 0, "Date": "Dec 2024", "YTD P&L": 0}, {"Well Name": "EE JONES UNIT 1", "Recent Month P&L": -5050.21, "YTD Gain/Loss": -50674.503110058, "Date": "Dec 2024", "YTD P&L": -50674.503110058}, {"Well Name": "EVA #1", "Recent Month P&L": 11540.9825230289, "YTD Gain/Loss": 80309.0412862354, "Date": "Dec 2024", "YTD P&L": 80309.0412862354}, {"Well Name": "FEATHER CREST FARMS #1", "Recent Month P&L": 12349.5821153848, "YTD Gain/Loss": 158645.1322195908, "Date": "Dec 2024", "YTD P&L": 158645.1322195908}, {"Well Name": "FRIDEL #1", "Recent Month P&L": -712.08, "YTD Gain/Loss": -8667.17, "Date": "Dec 2024", "YTD P&L": -8667.17}, {"Well Name": "Smith Georgette #1", "Recent Month P&L": -3116.18, "YTD Gain/Loss": -25629.2024830947, "Date": "Dec 2024", "YTD P&L": -25629.2024830947}, {"Well Name": "HERBICH #1H", "Recent Month P&L": 1527.9666348504, "YTD Gain/Loss": -83507.94768622, "Date": "Dec 2024", "YTD P&L": -83507.94768622}, {"Well Name": "KADAV #1", "Recent Month P&L": -10493.1142366408, "YTD Gain/Loss": -21643.4953364574, "Date": "Dec 2024", "YTD P&L": -21643.4953364574}, {"Well Name": "KNOTTS UNIT #1", "Recent Month P&L": 0, "YTD Gain/Loss": -1636.12, "Date": "Dec 2024", "YTD P&L": -1636.12}, {"Well Name": "Knotts-Yeager Unit #1", "Recent Month P&L": 1044.501695975, "YTD Gain/Loss": -18759.83620855, "Date": "Dec 2024", "YTD P&L": -18759.83620855}, {"Well Name": "Leon T-Bar-X Unit 1", "Recent Month P&L": -3884.6, "YTD Gain/Loss": -34188.7184, "Date": "Dec 2024", "YTD P&L": -34188.7184}, {"Well Name": "LLOYD #1", "Recent Month P&L": -711, "YTD Gain/Loss": -8235.13, "Date": "Dec 2024", "YTD P&L": -8235.13}, {"Well Name": "Mcduffie Unit #1", "Recent Month P&L": -12371.8395869615, "YTD Gain/Loss": 13444.602646395, "Date": "Dec 2024", "YTD P&L": 13444.602646395}, {"Well Name": "MOSLEY #1", "Recent Month P&L": 9231.6374819255, "YTD Gain/Loss": 127667.652565829, "Date": "Dec 2024", "YTD P&L": 127667.652565829}, {"Well Name": "Murphey-Smith #1", "Recent Month P&L": 11127.073042375, "YTD Gain/Loss": 62089.89695884, "Date": "Dec 2024", "YTD P&L": 62089.89695884}, {"Well Name": "Ortiz Unit #1", "Recent Month P&L": -3317.11, "YTD Gain/Loss": -23415.9330175406, "Date": "Dec 2024", "YTD P&L": -23415.9330175406}, {"Well Name": "OWEN #1", "Recent Month P&L": -3662.363169963, "YTD Gain/Loss": 39838.0570553945, "Date": "Dec 2024", "YTD P&L": 39838.0570553945}, {"Well Name": "OZELLE DAVIS UNIT #1 H", "Recent Month P&L": 0, "YTD Gain/Loss": 0, "Date": "Dec 2024", "YTD P&L": 0}, {"Well Name": "PETERS #5", "Recent Month P&L": -538.1366532064, "YTD Gain/Loss": -25936.5535531156, "Date": "Dec 2024", "YTD P&L": -25936.5535531156}, {"Well Name": "PETERS EE A #1", "Recent Month P&L": 0, "YTD Gain/Loss": -661.6, "Date": "Dec 2024", "YTD P&L": -661.6}, {"Well Name": "Sandifer Unit #1", "Recent Month P&L": -8899.87, "YTD Gain/Loss": -16524.2522, "Date": "Dec 2024", "YTD P&L": -16524.2522}, {"Well Name": "SOELL #1", "Recent Month P&L": -3205.06, "YTD Gain/Loss": -52795.5922354798, "Date": "Dec 2024", "YTD P&L": -52795.5922354798}, {"Well Name": "Spiller T-Bar-X #1", "Recent Month P&L": -6582.01, "YTD Gain/Loss": -82974.3362382664, "Date": "Dec 2024", "YTD P&L": -82974.3362382664}, {"Well Name": "TIMOTHY #1", "Recent Month P&L": -9151.12, "YTD Gain/Loss": -16387.7434384273, "Date": "Dec 2024", "YTD P&L": -16387.7434384273}, {"Well Name": "Total", "Recent Month P&L": 22556.5785883198, "YTD Gain/Loss": 487627.813853029, "Date": "Dec 2024", "YTD P&L": 487627.813853029}, {"Well Name": "Warren #1H", "Recent Month P&L": 35861.011051852, "YTD Gain/Loss": 424741.3517544468, "Date": "Dec 2024", "YTD P&L": 424741.3517544468}, {"Well Name": "WENDEL #1", "Recent Month P&L": 0, "YTD Gain/Loss": 0, "Date": "Dec 2024", "YTD P&L": 0}, {"Well Name": "WENDEL RIOUX", "Recent Month P&L": 0, "YTD Gain/Loss": 0, "Date": "Dec 2024", "YTD P&L": 0}, {"Well Name": "Wickson Unit #1", "Recent Month P&L": -371.57, "YTD Gain/Loss": -37241.8377688344, "Date": "Dec 2024", "YTD P&L": -37241.8377688344}, {"Well Name": "Wilson #1", "Recent Month P&L": 13339.3553970645, "YTD Gain/Loss": 79420.435000686, "Date": "Dec 2024", "YTD P&L": 79420.435000686}]