[{"Well Name":"Bruce Weaver #1","Date":"2023-11-20","Oil (BBLS)":5.0,"Gas (MCF)":0.0,"Water (BBLS)":0.0,"TP":150.0,"CP":20.0,"Comments":"On to off","7DMA":4.1,"30DMA":7.1,"MA Ratio":0.58},{"Well Name":"CR #101","Date":"2023-11-20","Oil (BBLS)":0.0,"Gas (MCF)":103.0,"Water (BBLS)":0.0,"TP":120.0,"CP":60.0,"Comments":"Unit on per schedule","7DMA":13.8,"30DMA":13.5,"MA Ratio":1.02},{"Well Name":"CR #201","Date":"2023-11-20","Oil (BBLS)":0.0,"Gas (MCF)":94.0,"Water (BBLS)":0.0,"TP":60.0,"CP":40.0,"Comments":"Unit left on extra day for hot oil\nComp on","7DMA":13.4,"30DMA":11.4,"MA Ratio":1.18},{"Well Name":"CR #301","Date":"2023-11-20","Oil (BBLS)":0.0,"Gas (MCF)":371.0,"Water (BBLS)":0.0,"TP":0.0,"CP":47.96,"Comments":"Unit on (hot oiler on location)","7DMA":19.3,"30DMA":20.4,"MA Ratio":0.95},{"Well Name":"CR #501","Date":"2023-11-20","Oil (BBLS)":0.0,"Gas (MCF)":0.0,"Water (BBLS)":0.0,"TP":30.0,"CP":30.0,"Comments":"Unit off","7DMA":0.6,"30DMA":6.7,"MA Ratio":0.09},{"Well Name":"CT #1","Date":"2023-11-20","Oil (BBLS)":0.0,"Gas (MCF)":16.0,"Water (BBLS)":0.0,"TP":0.0,"CP":30.0,"Comments":"Rig on well","7DMA":11.4,"30DMA":33.8,"MA Ratio":0.34},{"Well Name":"Carolpick #1","Date":"2023-11-20","Oil (BBLS)":0.0,"Gas (MCF)":21.0,"Water (BBLS)":0.0,"TP":50.0,"CP":20.0,"Comments":"Off to on","7DMA":6.9,"30DMA":11.6,"MA Ratio":0.59},{"Well Name":"Carolyn #1","Date":"2023-11-20","Oil (BBLS)":0.0,"Gas (MCF)":0.0,"Water (BBLS)":0.0,"TP":75.0,"CP":30.0,"Comments":"Unit was down, added fluids to motor but motor had a constant backfire, notified mechanics","7DMA":3.3,"30DMA":14.7,"MA Ratio":0.22},{"Well Name":"Dunkle #2","Date":"2023-11-20","Oil (BBLS)":0.0,"Gas (MCF)":0.0,"Water (BBLS)":0.0,"TP":100.0,"CP":40.0,"Comments":"Unit on","7DMA":11.5,"30DMA":7.9,"MA Ratio":1.46},{"Well Name":"Flower #1","Date":"2023-11-20","Oil (BBLS)":0.0,"Gas (MCF)":0.0,"Water (BBLS)":0.0,"TP":120.0,"CP":25.0,"Comments":"Unit on compressor on","7DMA":11.3,"30DMA":14.1,"MA Ratio":0.8},{"Well Name":"Gail #1","Date":"2023-11-20","Oil (BBLS)":0.0,"Gas (MCF)":0.0,"Water (BBLS)":0.0,"TP":50.0,"CP":20.0,"Comments":"Unit down with mechanical issues","7DMA":0.0,"30DMA":8.2,"MA Ratio":0.0},{"Well Name":"JIC #1","Date":"2023-11-20","Oil (BBLS)":0.0,"Gas (MCF)":0.0,"Water (BBLS)":0.0,"TP":374.89,"CP":416.31,"Comments":null,"7DMA":11.7,"30DMA":37.1,"MA Ratio":0.32},{"Well Name":"Jessica #1","Date":"2023-11-20","Oil (BBLS)":0.0,"Gas (MCF)":136.0,"Water (BBLS)":0.0,"TP":100.0,"CP":90.0,"Comments":"Comp getting fixed due to production issues on compressor not working correctly","7DMA":2.2,"30DMA":7.3,"MA Ratio":0.3},{"Well Name":"Jred #1","Date":"2023-11-20","Oil (BBLS)":7.0,"Gas (MCF)":0.0,"Water (BBLS)":0.0,"TP":160.0,"CP":20.0,"Comments":"Unit on","7DMA":13.8,"30DMA":21.2,"MA Ratio":0.65},{"Well Name":"Kay #1","Date":"2023-11-20","Oil (BBLS)":0.0,"Gas (MCF)":123.0,"Water (BBLS)":8.0,"TP":100.0,"CP":10.0,"Comments":"Unit on compressor on","7DMA":14.8,"30DMA":22.3,"MA Ratio":0.66},{"Well Name":"Kiley #1","Date":"2023-11-20","Oil (BBLS)":26.7,"Gas (MCF)":92.0,"Water (BBLS)":35.0,"TP":100.0,"CP":50.0,"Comments":null,"7DMA":24.8,"30DMA":35.3,"MA Ratio":0.7},{"Well Name":"La Rosita #1 RE","Date":"2023-11-20","Oil (BBLS)":177.1,"Gas (MCF)":90.0,"Water (BBLS)":0.0,"TP":140.0,"CP":0.0,"Comments":"Oil from frack tank # 2807531 11\/20\/2023 est gross 190.0 est net 188.14","7DMA":164.2,"30DMA":274.8,"MA Ratio":0.6},{"Well Name":"Lamb #1","Date":"2023-11-20","Oil (BBLS)":0.0,"Gas (MCF)":0.0,"Water (BBLS)":0.0,"TP":625.0,"CP":null,"Comments":null,"7DMA":0.0,"30DMA":6.6,"MA Ratio":0.0},{"Well Name":"Marrs #1","Date":"2023-11-20","Oil (BBLS)":0.0,"Gas (MCF)":18.0,"Water (BBLS)":0.0,"TP":150.0,"CP":112.79,"Comments":"Unit was down, put BOL","7DMA":21.0,"30DMA":23.9,"MA Ratio":0.88},{"Well Name":"Thalmann #1","Date":"2023-11-20","Oil (BBLS)":0.0,"Gas (MCF)":0.0,"Water (BBLS)":0.0,"TP":20.0,"CP":20.0,"Comments":"Unit on per schedule","7DMA":0.0,"30DMA":6.1,"MA Ratio":0.0},{"Well Name":"Trotter #1","Date":"2023-11-20","Oil (BBLS)":5.0,"Gas (MCF)":0.0,"Water (BBLS)":3.0,"TP":40.0,"CP":10.0,"Comments":null,"7DMA":5.7,"30DMA":9.1,"MA Ratio":0.63}]